mersal_litestar/__init__.py
mersal_litestar/litestar_mersal_plugin.py
mersal_litestar/py.typed
mersal_litestar-0.1.0.dist-info/METADATA
mersal_litestar-0.1.0.dist-info/WHEEL
mersal_litestar-0.1.0.dist-info/RECORD
